anti_gaslighting/gs.py
anti_gaslightning-0.0.3.dist-info/METADATA
anti_gaslightning-0.0.3.dist-info/WHEEL
anti_gaslightning-0.0.3.dist-info/entry_points.txt
anti_gaslightning-0.0.3.dist-info/top_level.txt
anti_gaslightning-0.0.3.dist-info/RECORD
