Metadata-Version: 2.4
Name: anti_gaslightning
Version: 0.0.3
Summary: A small example package
Author-email: Oscar Bahamonde <oscar.bahamonde@pucp.pe>
Classifier: Programming Language :: Python :: 3
Classifier: License :: OSI Approved :: MIT License
Classifier: Operating System :: OS Independent
Requires-Python: >=3.7
Requires-Dist: bleak
Requires-Dist: click>=8.1.8
Requires-Dist: groq>=0.11.0
Requires-Dist: pyaudio>=0.2.14
Requires-Dist: rich>=13.8.1
